framelesswindow/__init__.py
framelesswindow/_rc/__init__.py
framelesswindow/_rc/resource.py
framelesswindow/linux/__init__.py
framelesswindow/linux/window_effect.py
framelesswindow/mac/__init__.py
framelesswindow/mac/window_effect.py
framelesswindow/titlebar/__init__.py
framelesswindow/titlebar/title_bar_buttons.py
framelesswindow/utils/__init__.py
framelesswindow/utils/linux_utils.py
framelesswindow/utils/mac_utils.py
framelesswindow/utils/win32_utils.py
framelesswindow/webengine/__init__.py
framelesswindow/windows/__init__.py
framelesswindow/windows/c_structures.py
framelesswindow/windows/window_effect.py
fhframelesswindow-0.1.2.dist-info/METADATA
fhframelesswindow-0.1.2.dist-info/WHEEL
fhframelesswindow-0.1.2.dist-info/RECORD
