Metadata-Version: 2.1
Name: fhframelesswindow
Version: 0.1.2
Summary: A cross-platform frameless window based on pyside2, support Win32, Linux and macOS.
Author: wsd
Author-email: wsd@fhit.cn
Requires-Python: >=3.8,<4.0
Classifier: Programming Language :: Python :: 3
Classifier: Programming Language :: Python :: 3.8
Classifier: Programming Language :: Python :: 3.9
Classifier: Programming Language :: Python :: 3.10
Classifier: Programming Language :: Python :: 3.11
Classifier: Programming Language :: Python :: 3.12
Classifier: Programming Language :: Python :: 3.13
